alibabacloud_ecd20200930/__init__.py
alibabacloud_ecd20200930/client.py
alibabacloud_ecd20200930/models/__init__.py
alibabacloud_ecd20200930/models/_activate_office_site_request.py
alibabacloud_ecd20200930/models/_activate_office_site_response.py
alibabacloud_ecd20200930/models/_activate_office_site_response_body.py
alibabacloud_ecd20200930/models/_add_desktop_oversold_user_group_request.py
alibabacloud_ecd20200930/models/_add_desktop_oversold_user_group_response.py
alibabacloud_ecd20200930/models/_add_desktop_oversold_user_group_response_body.py
alibabacloud_ecd20200930/models/_add_devices_request.py
alibabacloud_ecd20200930/models/_add_devices_response.py
alibabacloud_ecd20200930/models/_add_devices_response_body.py
alibabacloud_ecd20200930/models/_add_file_permission_request.py
alibabacloud_ecd20200930/models/_add_file_permission_response.py
alibabacloud_ecd20200930/models/_add_file_permission_response_body.py
alibabacloud_ecd20200930/models/_add_file_permission_shrink_request.py
alibabacloud_ecd20200930/models/_add_user_to_desktop_group_request.py
alibabacloud_ecd20200930/models/_add_user_to_desktop_group_response.py
alibabacloud_ecd20200930/models/_add_user_to_desktop_group_response_body.py
alibabacloud_ecd20200930/models/_add_user_to_desktop_oversold_user_group_request.py
alibabacloud_ecd20200930/models/_add_user_to_desktop_oversold_user_group_response.py
alibabacloud_ecd20200930/models/_add_user_to_desktop_oversold_user_group_response_body.py
alibabacloud_ecd20200930/models/_allocate_ip_address_request.py
alibabacloud_ecd20200930/models/_allocate_ip_address_response.py
alibabacloud_ecd20200930/models/_allocate_ip_address_response_body.py
alibabacloud_ecd20200930/models/_apply_auto_snapshot_policy_request.py
alibabacloud_ecd20200930/models/_apply_auto_snapshot_policy_response.py
alibabacloud_ecd20200930/models/_apply_auto_snapshot_policy_response_body.py
alibabacloud_ecd20200930/models/_apply_coordinate_privilege_request.py
alibabacloud_ecd20200930-4.21.4.dist-info/LICENSE
alibabacloud_ecd20200930-4.21.4.dist-info/METADATA
alibabacloud_ecd20200930-4.21.4.dist-info/WHEEL
alibabacloud_ecd20200930-4.21.4.dist-info/top_level.txt
alibabacloud_ecd20200930-4.21.4.dist-info/RECORD
